Workbook

Sheet Recap
A1: SUMMARY EXPENSES / REVENUS
A3: Earth month market 04/19/26 | D3: 65 clothes/accessories sold | E3: 16 home goods
A4: best friends pop-up 03/15/26 | D4: 59 items sold
A5: best friends pop-up 01/25/26 | D5: 49 items sold
A6: picnic pop up 12/6/25 | D6: 46 clothes sold | E6: 27 home goods | H6: Sales | I6: ='Women - Sold'!E2 +'Kids - SOLD'!E2+'Home goods - Sold'!E2+C8+C9+C10+C12+C13+C14 -> 24760.28
A7: pop up 11/15/25 | D7: 57 clothes sold
A8: market 10/05/25 | B8: revenu | C8: 707 | D8: 30 clothes | E8: 8 home goods
A9: solano stroll 2025 | B9: revenu | C9: 850 | D9: 36 clothes | E9: 12 home goods
A10: market 8/24 | B10: revenu | C10: 1218 | D10: 38 clothes | E10: 8 home goods
A11: pop up 6/14 | B11: revenu | D11: 7 clothes | F11: 165 total (included by item)
A12: Pop Up 5/17 | B12: revenu | C12: 500 | D12: 16 clothes | E12: 1 bag
A13: Bon Marché April 2025 | B13: revenu | C13: 1090 | D13: 38 clothes | E13: 20 home goods
A14: Bon Marché February 2025 | B14: revenu | C14: 1060
A15: women clothes purchase | B15: expense | C15: =-(Women!D2+'Women - Sold'!D2) -> -10069.04
A16: women clothes sold | B16: revenu | C16: ='Women - Sold'!E2 -> 16193.83
A17: women clothes shipping | B17: expense | C17: =-'Women - Sold'!F2 -> -762.51
A18: home goods purchase | B18: expense | C18: =-('Home goods'!D2+'Home goods - Sold'!D2) -> -1481.41
A19: home goods sold | B19: revenu | C19: ='Home goods - Sold'!E2 -> 2579.45
A20: kids purchases | B20: expense | C20: =-(Kids!D2+'Kids - SOLD'!D2) -> -176.9
A21: Kids sold | B21: revenu | C21: ='Kids - SOLD'!G2 -> 460.6
C23: =SUM(C8:C21) -> 12169.02

Sheet Women
A1: Brand | B1: what? | C1: size | D1: cost | E1: Sold | F1: Shipping | G1: Benefice net | H1: Market price | I1: Link
D2: =SUM(D3:D990) -> 4985.43
A3: 360 cashmere | B3: beige cashmere sweater | C3: S | D3: 10
A4: 7 for all mankind | B4: black cropped jeans | C4: 27 | D4: 4
A5: 7 for all mankind | B5: blue jeans | C5: 29
A6: A new day | B6: teal babydoll dress | C6: M | D6: 9
A7: abercrombie | B7: black tank top | C7: M | D7: 2.5
A8: Active USa | B8: black LS top | C8: S | D8: 6
A9: Adolfo Dominguez | B9: blue linen top | C9: 38
A10: AERO | B10: khaki sweatpants | C10: XS
A11: AGL | B11: bordeaux shoes | C11: 38 | D11: 4.5
A12: Agnes B | B12: white LS top | D12: 6.5
A13: Akashi Kama | B13: green jacket | C13: S | D13: 10
A14: Alessandra Olivia | B14: green linen top | C14: S | D14: 5
A15: Alessandra Olivia | B15: blue linen top | C15: XS | D15: 5
A16: Alessia Pacini | B16: white linen blouse | C16: S | D16: 6
A17: Alessia Pacini | B17: cream linen jacket | C17: S | D17: 6.5
A18: Alex Mill | B18: blue pants | C18: 6 | D18: 3
A19: All Bird | B19: black wool sneakers | C19: 9 | D19: 2.5
A20: American Eagle | B20: cream dress, SS | C20: S | D20: 6 | H20: stain
A21: American Eagle | B21: blue/red dress | C21: 2
A22: american giant | B22: cotton hoodie | C22: XS | D22: 5
A23: amour vert | B23: white/beige LS top | C23: S | D23: 5
A24: amour vert | B24: black/green LS top | C24: XS | D24: 6
A25: amour vert | B25: navy silk dress | C25: S | D25: 9
A26: amour vert | B26: grey LS top | C26: S | D26: 6.5
A27: amour vert | B27: green wool cropped sweater | C27: S | D27: 3
A28: amour vert | B28: floral SS top | C28: L | D28: 3
A29: amour vert | B29: black white dots top | C29: XS | D29: 5
A30: amour vert | B30: grey stripes tee | C30: S | D30: 5
A31: amour vert | B31: BW chevron sweater | C31: XS | D31: 10
A32: amour vert | B32: grey top LS with front knot | C32: XS | D32: 7.3
A33: amour vert | B33: navy/white dress | C33: M | D33: 10
... A35: amour vert | B35: navy wool cardigan | C35: XS | D35: 20
A36: amour vert | B36: black jacket | C36: S
A37: amour vert | B37: black top LS vneck | C37: XS | D37: 8.1
A38: Amour vert | B38: beige wool skirt | C38: M | D38: 7.3
A39: Andantini | B39: leather cross body bag | D39: 15
A40: ann taylor | B40: black cashmerre turtleneck | C40: XS | D40: 12.5
A41: anne Klein | B41: navy silk blouse | C41: 8P | D41: 6
A42: anthropologie | B42: white/blue stripes linen pants | C42: M | D42: 5
A43: anthropologie | B43: red pants | C43: 4 | D43: 8.5
A44: anthropologie | B44: blue long cocktail dress | C44: XS | D44: 20
A45: anthropologie | B45: beige top blue dots | C45: S | D45: 6
A46: anthropologie | B46: blue ruffle top | C46: XXS | D46: 6
A47: anthropologie | B47: black mini dress | C47: XS | D47: 7.5
A48: Aqua cashmere | B48: grey frenchy sweater | C48: XS | D48: 4.25
A49: Aqua cashmere | B49: cream turtleneck cashmere | C49: M | D49: 9
A50: Aran | B50: dark pink wool cardigan | C50: M | D50: 4.25
A51: Aritzia | B51: navy wool cableknit sweater | C51: XXS | D51: 8.5
A52: Armani collezioni | B52: bouclé jacket | C52: 8 | D52: 9
A53: Armor Lux | B53: navy wool sweater | C53: 0 | D53: 10
A54: artclass | B54: black tank top | C54: 12yo
A55: asian eyes | B55: wool scarf | D55: 3.5
A56: athleta | B56: cream wool turtleneck | C56: S | D56: 5 | G56: stained
A57: athleta | B57: light grey hoodie cotton/tencel | C57: M | D57: 5.5
A58: athleta | B58: beige SS shirt | C58: XS | D58: 6
A59: athleta | B59: beige wool dress | C59: S | D59: 10
A60: athleta | B60: cream cashmere open cardigan | C60: S | D60: 7.3
A61: athleta | B61: girl cardigan | C61: 45879 | D61: 5
A62: athleta | B62: grey/white legging | C62: S | D62: 10
A63: athleta | B63: grey hoody SS | C63: XS | D63: 4
A64: audrey brooke | B64: leather sandals | C64: 8 | D64: 9
A65: Australian | B65: red/navy wool sweater | D65: 9
A66: Bally | B66: navy merino cardigan | D66: 3.25
A67: banana R | B67: teal cashmere sweater | C67: S | D67: 6 | H67: needs a repair
A68: banana R | B68: tan long dress | C68: XS | D68: 11
A69: banana R | B69: coral merino sweater | C69: S | D69: 5
A70: banana R | B70: bordeaux cardigan silk/cotton | C70: XS | D70: 3.25
A71: banana R | B71: BW pinstripes shirt | C71: S | D71: 5
A72: banana R | B72: black tiger sweater silk/cashmere | C72: M | D72: 8.5
A73: banana R | B73: silk LS shirt | C73: M | D73: 7.5
A74: banana R | B74: giraffe cotton sweater | C74: M | D74: 10
A75: banana R | B75: black organic wool dress | C75: L | D75: 11
A76: banana R | B76: forest green wool sweater | C76: M | D76: 6.49
A77: banana R | B77: black merino wool sweater | C77: XS | D77: 6.5
A78: banana R | B78: heathered red linen/cotton shirt | C78: M | D78: 5
A79: banana R | B79: blue wool cardigan | C79: XS | D79: 6
... A82: banana R | B82: beige merino cardigan | C82: S | D82: 3.65
A83: banana R | B83: chambray pants | C83: 6 | D83: 4
A84: banana R | B84: black merino sweater SS | C84: S | D84: 3
A85: banana R | B85: new - tan SL cashmere top | C85: S | D85: 8.5
A86: banana R | B86: navy sweater with back knot | C86: M | D86: 7.3
A87: banana R | B87: large brown wool blend sweater | C87: XS | D87: 10
A88: banana R | B88: Silk blend dark pink turtleneck | C88: S | D88: 10
A89: banana R | B89: merino wool cream sweater | C89: S | D89: 10
A90: banana R | B90: dark grey wool cardigan | C90: S | D90: 9
A91: banana R | B91: black/white boho blouse | C91: S | D91: 7
A92: banana R | B92: brown silk skirt | C92: 4 | D92: 6
A93: banana R | B93: denim shorts | C93: 2P
A94: banana R | B94: cream/brown wool coat | C94: XS | D94: 8.5
A95: banana R | B95: beige linen cardigan | C95: S | D95: 5
A96: Banana R | B96: blue silk dress | C96: 2 | H96: stains
A97: Banana R | B97: Light grey sweater cotton/silk | C97: S | D97: 10
A98: Banana R | B98: pink filpucci sweater | C98: XS | D98: 9
A99: Banana R | B99: sleeveless purple top | C99: S | H99: needs a repair
A100: Banana R | B100: beige city chino pants | C100: 4
A101: Banana R | B101: khaki pants | C101: 28
A102: BA&sh | B102: coral blouse | C102: S | D102: 5.5
A103: BCBG Max Azria | B103: coral silk blouse | C103: XXS | D103: 6.5 | G103: has a stain
...

Sheet Women - Sold
A1: Brand | B1: what? | C1: size | D1: cost | E1: Sold | F1: Shipping | G1: Benefice net | H1: Event | I1: Link
D2: =SUM(D3:D1250) -> 5083.61 | E2: =SUM(E3:E1250) -> 16193.83 | F2: =SUM(F3:F1250) -> 762.51
A3: 1045 park | B3: vintage black top | C3: 5 | D3: 4 | E3: 25 | F3: 0 | G3: =E3-F3-D3 -> 21 | H3: picnic
A4: 120 Lino | B4: black/white dots shirt | C4: 44 | D4: 6 | E4: 30 | F4: 0 | G4: =E4-F4-D4 -> 24 | H4: 46131
A5: abercrombie | B5: dark blue/black sweater puff S | C5: S | D5: 0 | H5: 45767
A6: abercrombie | B6: blue peasant shirt | C6: M | D6: 7 | H6: solano stroll
A7: abercrombie | B7: blue open cardigan | C7: XS/S | H7: 45893
A8: A new day | B8: long brick dress | C8: S | D8: 7.49 | E8: 31.5 | F8: 6.35 | G8: =E8-F8-D8 -> 17.66
A9: Adidas | B9: black jacket | C9: S | H9: solano stroll | I9: sold 30
A10: Agnes B | B10: black tee | D10: 5 | E10: 20 | F10: 0 | G10: =E10-F10-D10 -> 15 | H10: 46131
A11: Agnes B | B11: Blue sweater | C11: 2 | D11: 8.1 | E11: 77.43 | F11: 4.49 | G11: =E11-F11-D11 -> 64.84 | H11: NB
A12: aiavu | B12: cashmere stripe sweater | C12: M | D12: 3.5 | E12: 67.84 | F12: 5.37 | G12: =E12-F12-D12 -> 58.97 | H12: NB
A13: Alex Mill | B13: Blue linen shirt | C13: M | D13: 9 | E13: 35 | F13: 0 | G13: =E13-D13 -> 26 | H13: 46096
A14: Alfani | B14: teal merino wool sweater | C14: S | D14: 7 | E14: 25 | F14: 0 | G14: =E14-D14 -> 18 | H14: 46047
A15: Allen Solly | B15: vintage wool vest | C15: S | D15: 10 | E15: 36.39 | F15: 6.39 | G15: =E15-F15-D15 -> 20
A16: Alynn | B16: silk scarf with books | D16: 1.5 | H16: 45696 | I16: gift
A17: American Eagle | B17: navy/grey sweater | C17: S | H17: 45893
A18: Amour vert | B18: navy blue wrap shirt | C18: M | D18: 13 | E18: 36 | F18: 0 | G18: =E18-F18-D18 -> 23 | H18: MT
A19: amour vert | B19: white tank top | C19: M | D19: 10 | H19: 45893
A20: amour vert | B20: red wool sweater | C20: S | D20: 4 | E20: 30 | F20: 0 | G20: =E20-F20-D20 -> 26 | H20: 45976
A21: amour vert | B21: cream SL knitted top | C21: XS | D21: 5 | E21: 30 | F21: 0 | G21: =E21-D21 -> 25 | H21: 46096
A22: Amour vert | B22: grey open cardigan | C22: M | D22: 7 | E22: 30 | F22: 0 | G22: =E22-F22-D22 -> 23 | H22: picnic
A23: amour vert | B23: green floral top | C23: XS | D23: 17 | H23: solano stroll
A24: amour vert | B24: silk jumpsuit | C24: M | D24: 5 | E24: 50 | F24: 3.47 | G24: =E24-F24-D24 -> 41.53
A25: amour vert | B25: silk floral blouse | C25: SP | D25: 7 | E25: 25 | F25: 0 | G25: =E25-F25-D25 -> 18 | H25: 45822
A26: Amour vert | B26: silk shirt | C26: M | D26: 10 | E26: 25 | F26: 3.5 | G26: =E26-F26-D26 -> 11.5 | I26: dry cleaner
A27: amour vert | B27: pink silk dress | C27: S | H27: 45696 | I27: sold $50
A28: Andrea Mabiani | B28: Blue leather bag | D28: 9 | H28: 45696 | I28: sold $40
A29: ann taylor | B29: black cashmere cardigan | C29: S | D29: 8.5 | E29: 40 | F29: 0 | G29: =E29-F29-D29 -> 31.5
A30: Ann Taylor | B30: black/brown/cream sweater | C30: S | D30: 8 | E30: 20 | F30: 0 | G30: =E30-F30-D30 -> 12
A31: ann taylor | B31: blue cashmere sweater | C31: M | D31: 15 | E31: 30 | F31: 0 | G31: =E31-F31-D31 -> 15
A32: Anne Fernwood | B32: vintage brown shirt | D32: 6.5 | E32: 25 | F32: 0 | G32: =E32-D32 -> 18.5 | H32: 46096
A33: anthropologie | B33: edme grey floral top | C33: 2 | D33: 6.3 | E33: 15 | F33: 0 | G33: =E33-F33-D33 -> 8.7
A34: anthropologie | B34: pink cardigan with front design | C34: S | D34: 3.7 | E34: 25 | F34: 0 | G34: =E34-D34 -> 21.3 | H34: 46131
A35: anthropologie | B35: embroidered multicolor blouse | C35: S | D35: 6 | E35: 25 | F35: 0 | G35: =E35-D35 -> 19 | H35: 46131
A36: anthropologie | B36: SL red/pink blouse | C36: XL | D36: 6.3 | H36: 45767
A37: anthropologie | B37: long dress terracotta | C37: L | D37: 10 | H37: 45767
A38: anthropologie | B38: tropical dress | C38: XS | D38: 11 | H38: 45767
A39: anthropologie | B39: kakhi pants | C39: SP | D39: 10 | H39: 45794
A40: Aqua cashmere | B40: cream cashmere sweater | C40: S | D40: 9 | E40: 40 | F40: 0 | G40: =E40-D40 -> 31 | H40: 46096
A41: Aqua cashmere | B41: cream cashmere sweater | C41: L | D41: 11 | E41: 40 | F41: 0 | G41: =E41-D41 -> 29
A42: Armor Lux | B42: stripe tshirt | C42: M | D42: 7.1 | H42: 45893
A43: artclass | B43: black LS shirt | C43: 45942 | H43: solano stroll
A44: Ateesa | B44: navy SL top with green stripes | C44: M | D44: 6 | E44: 15 | F44: 0 | G44: =E44-F44-D44 -> 9
A45: athleta | B45: white crop top | C45: M | D45: 8 | H45: 45893
A46: athleta | B46: vintage wool cardigan | C46: M | D46: 8 | E46: 30 | F46: 0 | G46: =E46-F46-D46 -> 22 | H46: 45976
A47: athleta | B47: cashmere sweater, light grey | C47: S | D47: 4 | E47: 35 | F47: 0 | G47: =E47-D47 -> 31 | H47: 45976
A48: athleta | B48: dark green sweater | C48: S | D48: 10 | E48: 35 | F48: 0 | G48: =E48-D48 -> 25 | H48: 46047
A49: athleta | B49: blue linen pants | C49: 0 | D49: 4 | E49: 25 | F49: 0 | G49: =E49-D49 -> 21 | H49: 46131
A50: athleta | B50: dark purple cardigan | C50: S | D50: 11 | E50: 30 | F50: 0 | G50: =E50-D50 -> 19 | H50: 46131
A51: athleta | B51: large purple sweater | C51: S | D51: 13 | E51: 30 | F51: 0 | G51: =E51-F51-D51 -> 17 | H51: picnic
A52: athleta | B52: blue top open back | C52: M | D52: 8.1 | H52: solano stroll
A53: athleta | B53: navy tshirt | C53: M | D53: 7 | H53: solano stroll
A54: Athleta | B54: black sweatpants | C54: S | D54: 6.29 | E54: 30 | F54: 11.58 | G54: =E54-F54-D54 -> 12.13
A55: Athleta | B55: merino wool black sweater | C55: M | D55: 9 | E55: 20 | F55: 0 | G55: =E55-F55-D55 -> 11 | H55: MT
A56: Avalanche | B56: beige jacket | C56: M | D56: 7.5 | E56: 35 | F56: 0 | G56: =E56-D56 -> 27.5 | H56: 46096
A57: BA&sh | B57: black blouse | C57: 0 | D57: 7.19 | E57: 32 | F57: 0 | G57: =E57-D57 -> 24.81 | H57: MT
A58: Babette SF | B58: Wool scarf | D58: 3.5 | E58: 20 | F58: 0 | G58: =E58-D58 -> 16.5 | H58: 45976
A59: BAGGU | B59: Black leather bag | D59: 3.25 | H59: 45794
A60: banana R | B60: long black wool cardigan | C60: S | D60: 5 | E60: 25 | F60: 0 | G60: =E60-F60-D60 -> 20 | H60: 46096
A61: banana R | B61: stripes LS top | C61: XS | D61: 5.5 | E61: 25 | F61: 0 | G61: =E61-F61-D61 -> 19.5 | H61: 46096
A62: banana R | B62: burgundy silk SL top | C62: S | D62: 5 | E62: 25 | F62: 0 | G62: =E62-F62-D62 -> 20 | H62: 46096
A63: banana R | B63: beige SL top w/ turtleneck | C63: S | D63: 6 | E63: 30 | F63: 0 | G63: =E63-F63-D63 -> 24 | H63: 46096
A64: banana R | B64: vine silk/cashmere turtleneck | C64: XS | D64: 6.5 | E64: 25 | F64: 0 | G64: =E64-F64-D64 -> 18.5 | H64: 46047
A65: banana R | B65: raspberry sweater silk/cashmere | C65: M | D65: 10 | E65: 25 | F65: 0 | G65: =E65-F65-D65 -> 15 | H65: 46047
A66: Banana R | B66: wool blue/grey stripe sweater | C66: S | D66: 7 | E66: 25 | F66: 0 | G66: =E66-F66-D66 -> 18 | H66: 46047
A67: Banana R | B67: grey silk/cashmere sweater | C67: S | D67: 8.1 | E67: 25 | F67: 0 | G67: =E67-F67-D67 -> 16.9 | H67: 46047
A68: banana R | B68: rabbit hair sweater | C68: L | D68: 10 | E68: 30 | F68: 0 | G68: =E68-F68-D68 -> 20 | H68: 45976
A69: banana R | B69: rust wool scraf | D69: 2 | E69: 20 | F69: 0 | G69: =E69-F69-D69 -> 18 | H69: 45976
A70: Banana R | B70: pink cashmere scarf | D70: 2.5 | E70: 30 | F70: 0 | G70: =E70-F70-D70 -> 27.5 | H70: 45976
A71: banana R | B71: green silk top SL | C71: S | D71: 8 | H71: 45935
A72: Banana R | B72: cotton white blouse | C72: M | D72: 7 | E72: 23.2 | F72: 0 | G72: =E72-F72-D72 -> 16.2 | H72: MT
A73: Banana R | B73: red/blue ruffle top | C73: S | H73: 45893
A74: Banana R | B74: white texture blouse | C74: M | D74: 7 | H74: 45893
A75: banana R | B75: white linen sweater | C75: S | D75: 5 | E75: 20 | F75: 0 | G75: =E75-F75-D75 -> 15 | H75: 46131
A76: banana R | B76: navy/white stripes cotton cardigan | C76: S | D76: 5 | E76: 25 | F76: 0 | G76: =E76-D76 -> 20 | H76: 46131
A77: Banana R | B77: navy stripes cotton sweater | C77: XS | D77: 5 | E77: 20 | F77: 0 | G77: =E77-D77-F77 -> 15 | H77: 46131
A78: Banana R | B78: beige wool long cardigan | C78: XS | D78: 7 | E78: 20 | F78: 1.09 | G78: =E78-D78-F78 -> 11.91
A79: banana R | B79: purple wool sweater | C79: S | D79: 10 | E79: 25 | F79: 1.09 | G79: =E79-D79-F79 -> 13.91
A80: Banana R | B80: red merino wool men sweater | C80: M | D80: 4.5 | E80: 35.78 | F80: 0 | G80: =E80-F80-D80 -> 31.28
A81: Banana R | B81: black merino sweater | C81: XS | D81: 0 | E81: 15 | F81: 0 | G81: =E81-F81-D81 -> 15
A82: Banana R | B82: grey merino wool long cardigan | C82: S | D82: 4 | E82: 15 | F82: 0 | G82: =E82-D82 -> 11
A83: banana R | B83: brown wool/cotton sweater | C83: S | D83: 4.8 | E83: 27.07 | F83: 7.07 | G83: =E83-F83-D83 -> 15.2
A84: banana R | B84: 100% cashmere sweater BWpurple | C84: M | D84: 10 | E84: 33.5 | F84: 4.9 | G84: =E84-F84-D84 -> 18.6
A85: Banana R | B85: green merino sweater | C85: S | D85: 10 | E85: 20 | F85: 0 | G85: =E85-F85-D85 -> 10 | H85: picnic
A86: banana R | B86: beige sweater with hood | C86: S | D86: 6 | E86: 25 | F86: 0 | G86: =E86-F86-D86 -> 19 | H86: picnic
A87: Banana R | B87: black turtleneck sweater baby terry | C87: XS | H87: solano stroll
A88: Banana R | B88: red sweater Vneck | C88: M | D88: 8 | H88: solano stroll
A89: Banana R | B89: silk shirt / black | C89: L | D89: 10 | H89: 45794
A90: banana R | B90: pink SL blouse buttons in the back | C90: S | D90: 7.1 | H90: 45767
A91: Banana R | B91: light grey turtleneck | C91: M | D91: 4 | E91: 22.5 | F91: 5.5 | G91: =E91-F91-D91 -> 13
A92: Banana R | B92: navy long wool cardigan | C92: XS | D92: 10 | E92: 40 | F92: 5.39 | G92: =E92-F92-D92 -> 24.61
A93: Banana R | B93: black/white sweater | C93: XS | D93: 10 | E93: 30 | F93: 4.43 | G93: =E93-F93-D93 -> 15.57
A94: Banana R | B94: red silk blouse | C94: S | D94: 7 | E94: 25 | F94: 3.09 | G94: =E94-F94-D94 -> 14.91
A95: Banana R | B95: navy cotton sweater | C95: S | D95: 7 | E95: 20 | F95: 0 | G95: =E95-F95-D95 -> 13
A96: Banana R | B96: black merino wool | C96: L | D96: 10 | E96: 35 | F96: 4.51 | G96: =E96-F96-D96 -> 20.49
A97: Bass | B97: red floral shirt | C97: M | D97: 3.5 | E97: 20 | F97: 0 | G97: =E97-D97 -> 16.5 | H97: 46131
A98: BCBG | B98: Black silk dress | C98: S | D98: 10 | E98: 35 | F98: 4.22 | G98: =E98-F98-D98 -> 20.78
A99: beachlunchlounge | B99: multicolor shirt | C99: M | D99: 4 | E99: 25.77 | F99: 5.77 | G99: =E99-F99-D99 -> 16
A100: Bella Dahl | B100: black top LS | C100: S | D100: 6 | E100: 25 | F100: 0 | G100: =E100-D100 -> 19 | H100: 46047
...

Sheet Kids
A1: Brand | B1: what? | C1: size | D1: cost | E1: Sold | F1: Shipping | G1: Benefice net | H1: Market price | I1: Link
D2: =SUM(D5:D610) -> 86.65 | E2: =SUM(E11:E610) -> 0 | F2: =SUM(F11:F610) -> 0 | J2: 641
A3: angou | B3: floral jumpsuit | C3: 18mo | D3: 2
A4: art class | B4: black eyelet tank | C4: 12 | D4: 0
A5: art class | B5: green floral top | C5: 8 | D5: 0
A6: art class | B6: green tank top | C6: 6 | D6: 0
A7: baby organic | B7: jumsuit NWT | C7: 9mo | D7: 3
A8: banana republic | B8: yellow wool sweater | C8: M | D8: 9
A9: Bonpoint | B9: dark blue corduroy | C9: 4 | D9: 0
A10: bonpoint | B10: dark brown skirt | C10: 3 | D10: 0
A11: Boy + Girl | B11: stripe linen dress | C11: 6 | D11: 2 | I11: buttons changed
A12: Caramel | B12: dress with bloomer | C12: 1 | D12: 4
A13: Carter's | B13: brown jumpsuit | C13: 18mo | D13: 2
A14: Carter's | B14: white/gold onesie | C14: 2 | D14: 2.5
A15: cat and jack | B15: yellow cabana striped dress | C15: 11 | D15: 0
A16: cat and jack | B16: green jumpsuit | C16: 1 | D16: 1.5
A17: cat and jack | B17: turquoise dress | C17: 12 | D17: 0
A18: cat and jack | B18: light green dress | C18: 4 | D18: 3
A19: cat and jack | B19: BW skirt with bretelles | C19: 3 | D19: 4
A20: C&C California | B20: pink jacket | C20: 2 | D20: 2
A21: CFK | B21: navy shorts | C21: 5 | D21: 0
A22: CFK | B22: red stripes sweater | C22: 5 | D22: 0
A23: Cherokee | B23: denim vest | C23: 8 | D23: 0
A24: Cherokee | B24: blue/red/white stripes dress | C24: 8 | D24: 4
A25: club med | B25: swimming tee | D25: 0
A26: cotton on | B26: organic cotton white/grey pyjama | C26: 9mo | D26: 4
A27: crewcuts | B27: hot pink embroidery tunic | C27: 12 | D27: 0
A28: crewcuts | B28: navy/white stripes dress | C28: 10 | D28: 0
A29: cyrillus | B29: polka dots top | C29: 10 | D29: 0
A30: cyrillus | B30: peach dress | C30: 18m | D30: 0
A31: Destira | B31: gymnastics attire | D31: 0
A32: du pareil au meme | B32: dove sweater | C32: 5 | D32: 0
A33: Gap | B33: denim shorts with flowers | C33: 10 | D33: 5
A34: Gap kids | B34: tee bouées | C34: 8 | D34: 1
A35: grain de blé | B35: grey top | C35: 18m | D35: 0
A36: grayson mini | B36: stripes shorts | C36: 5 | D36: 1.15
A37: guess | B37: chambray jumpsuit | C37: 12 | D37: 0
A38: H&M | B38: black tank top | C38: 10 | D38: 0
A39: H&M | B39: tartan dress | C39: 1 | D39: 2.5
A40: H&M | B40: blue romper | C40: 18 | D40: 4
A41: Hannah Anderson | B41: cotton hat | D41: 2.5
A42: Hannah Anderson | B42: white turtleneck | C42: 14 | D42: 0
A43: Hill House | B43: blue cardigan | C43: 3mo | D43: 2
A44: Hope and henry | B44: white sweater dress | C44: 7 | D44: 8.5
A45: Jacadi | B45: salopette | C45: 4 | D45: 0
A46: Janie and Jack | B46: dark blue corduroy | C46: 4 | D46: 0
A47: Janie and Jack | B47: pumpkin pyjama | C47: 4 | D47: 2
A48: JCrew | B48: green LS tee | C48: 11 | D48: 2
A49: La queue du chat | B49: blue/cream tank top | C49: 4 | D49: 0
A50: La queue du chat | B50: pink dress blue balls | C50: 18m | D50: 0
A51: Les petits carreaux | B51: blue floral top | C51: 4 | D51: 0 | H51: stained
A52: Little co | B52: palm trees dress | C52: 5 | D52: 2
A53: Little Planet | B53: light brown onesie | C53: 18 | D53: 3.5
A54: Marèse | B54: navy blue knit dress | C54: 5 | D54: 0
A55: Monoprix | B55: bensimon skirt | C55: 4 | D55: 0
A56: Monoprix | B56: chambray skirt | C56: 12 | D56: 0
A57: Monoprix | B57: blue dress | C57: 12 | D57: 0
A58: Nohi | B58: pink ruffle skirt | C58: 2 | D58: 3
A59: old navy | B59: stripes summer set | C59: 5 | D59: 0
A60: old navy | B60: blue jumpsuit | C60: 8 | D60: 0
A61: old navy | B61: denim skirt | C61: 12 | D61: 0
A62: PACT | B62: red pyjama | C62: 10 | D62: 0
A63: petit bateau | B63: strip sweater | C63: 10 | D63: 0
A64: rebecca | B64: blue top | C64: 12 | D64: 0
A65: sergent major | B65: cream flower top | C65: 18m | D65: 0
A66: sergent major | B66: polka dots hat | D66: 0
A67: sfera girl | B67: brown skirt | C67: 10 | D67: 5
A68: The children's place | B68: jeans | C68: 8 | D68: 0
A69: tudobom | B69: pink dress | C69: 4 | D69: 0
A70: united colors of benetton | B70: linen/cotton kids shirt | C70: 45973 | D70: 1.5
A71: Zara | B71: chestnut sailor pants | C71: 5 | D71: 0

Sheet Kids - SOLD
A1: Brand | B1: what? | C1: size | D1: cost | E1: Sold | F1: Shipping | G1: Benefice net | H1: Market price | I1: Link
D2: =SUM(D5:D595) -> 90.25 | E2: =SUM(E5:E595) -> 562 | F2: =SUM(F5:F595) -> 11.15 | G2: =E2-F2-D2 -> 460.6 | I2: 1016.44 | J2: 641
A3: abercrombie kids | B3: navy ruffle dress | C3: 12 | D3: 2 | E3: 7.5 | F3: 0 | G3: =E3-D3-F3 -> 5.5 | H3: STC | I3: 46116
A4: baby gap | B4: pink coat | C4: 2 | D4: 4 | E4: 10.5 | F4: 0 | G4: =E4-D4-F4 -> 6.5 | H4: STC | J4: =E3+E8+E9+E10+E46+E52+E53 -> 40.5
A5: Carter's | B5: pyjama | C5: 6 | D5: 6 | E5: 4.5 | F5: 0 | G5: =E5-D5 -> -1.5 | H5: STC
A6: Carter's | B6: beige boy sweater with zipper | C6: 4 | D6: 2.5 | E6: 15 | F6: 0 | G6: =E6-F6-D6 -> 12.5
A7: cat and jack | B7: denim jacket | C7: 12 | D7: 0 | E7: 10 | F7: 0 | G7: =E7-F7-D7 -> 10
A8: cat and jack | B8: red/blue/white plaid dress | C8: 46211 | D8: 1.85 | E8: 4.5 | F8: 0 | G8: =E8-F8-D8 -> 2.65 | H8: STC | I8: 46142
A9: cat and jack | B9: Olive pinafore dress | C9: 4 | D9: 2 | E9: 4.5 | F9: 0 | G9: =E9-F9-D9 -> 2.5 | H9: STC | I9: 46122
A10: cat and jack | B10: rust long dress | C10: 12 | D10: 6.3 | E10: 4.5 | F10: 0 | G10: =E10-F10-D10 -> -1.8 | H10: STC | I10: 46116
A11: columbia | B11: 2 ski pants | D11: 0 | E11: 45 | F11: 0 | G11: =E11-F11-D11 -> 45
A12: crewcuts | B12: navy Brooklyn sweater | C12: 12 | D12: 8 | E12: 7.5 | F12: 0 | G12: =E12-F12-D12 -> -0.5 | H12: STC
A13: cynthia rowley | B13: unicorn sweater | C13: 4 | D13: 3.5 | E13: 10.5 | F13: 0 | G13: =E13-F13-D13 -> 7 | H13: STC
A14: everlane | B14: blue jacket | C14: 3 | D14: 6 | E14: 4.5 | F14: 0 | G14: =E14-F14-D14 -> -1.5 | H14: STC
A15: firsts impressions | B15: red sweater | C15: 9mo | D15: 5 | E15: 10 | F15: 0 | G15: =E15-F15-D15 -> 5
A16: gap | B16: floral jeans | C16: 12 | D16: 0 | E16: 7.5 | F16: 0 | G16: =E16-D16 -> 7.5 | H16: STC | I16: 46102
A17: Gap | B17: pink stripes LS tee | C17: 10 | D17: 0 | E17: 3 | F17: 0 | G17: =E17-D17 -> 3 | H17: STC
A18: gap | B18: pink shirt with embroidery | C18: 10 | D18: 0 | E18: 5 | F18: 0 | G18: =E18-F18-D18 -> 5
A19: H&M | B19: pink dress LS | C19: 7 | D19: 3 | E19: 10 | F19: 0 | G19: =E19-F19-D19 -> 7
A20: H&M | B20: pink floral blouse | C20: 12 | D20: 0 | E20: 5 | F20: 0.4 | G20: =E20-F20-D20 -> 4.6
A21: h&M | B21: blue stripes top | C21: 7 | D21: 0 | E21: 4.5 | F21: 0 | G21: =E21-F21-D21 -> 4.5 | H21: STC | I21: 46082
A22: H&M | B22: libellules cardigan | C22: 8 | D22: 0 | E22: 7.5 | F22: 0 | G22: =E22-F22-D22 -> 7.5 | H22: STC
A23: handmade | B23: pink cotton cardigan | C23: 3 | D23: 2.5 | E23: 20 | F23: 0 | G23: =E23-F23-D23 -> 17.5
A24: Hannah Anderson | B24: girls dress checkers | C24: 4 | D24: 3 | E24: 15 | F24: 0 | G24: =E24-F24-D24 -> 12
A25: Hannah Anderson | B25: fair Isle sweater | C25: 12 | D25: 0 | E25: 9 | F25: 0 | G25: =E25-F25-D25 -> 9 | H25: STC
A26: HM | B26: cat dress | C26: 3 | D26: 0 | E26: 5 | F26: 0 | G26: =E26-F26-D26 -> 5 | H26: picnic
A27: jacadi | B27: snow suit | C27: 18mo | D27: 0 | E27: 60 | F27: 0 | G27: =E27-F27-D27 -> 60
A28: La queue du chat | B28: blue overall | C28: 3 | D28: 0 | E28: 15 | F28: 1.25 | G28: =E28-F28-D28 -> 13.75
A29: La queue du chat | B29: pink dress | C29: 4 | D29: 0 | E29: 15 | F29: 1.25 | G29: =E29-F29-D29 -> 13.75
A30: M&S | B30: pink LS blouse | C30: 2 | D30: 2 | E30: 10 | F30: 0 | G30: =E30-F30-D30 -> 8
A31: Monoprix | B31: bensimon bloomer | C31: 3 | D31: 0 | E31: 6 | F31: 0 | G31: =E31-D31-F31 -> 6 | I31: 46106
A32: Monoprix | B32: red floral dress | C32: 4 | D32: 0 | E32: 7.5 | F32: 0 | G32: =E32-D32-F32 -> 7.5 | H32: STC | I32: 46100
A33: Monoprix | B33: red stripes overall | C33: 3 | D33: 0 | E33: 10 | F33: 1.25 | G33: =E33-F33-D33 -> 8.75
A34: Old Navy | B34: flower dress LS | C34: 8 | D34: 5 | E34: 10 | F34: 0 | G34: =E34-F34-D34 -> 5
A35: old navy | B35: red skirt | C35: 2 | D35: 2 | E35: 5 | F35: 1.25 | G35: =E35-F35-D35 -> 1.75
A36: old navy | B36: pink denim skirt | C36: 12 | D36: 0 | E36: 4.5 | F36: 0 | G36: =E36-D36 -> 4.5 | H36: STC | I36: 46109
A37: old navy | B37: beige floral top | C37: 8 | D37: 0 | E37: 4.5 | F37: 0 | G37: =E37-D37 -> 4.5 | H37: STC
A38: Old Navy | B38: jean shorts | C38: 10yo | D38: 0 | E38: 4.5 | F38: 0 | G38: =E38-D38 -> 4.5 | H38: STC
A39: Osh Kosh | B39: sparkle sweater | C39: 3 | D39: 0 | E39: 4.5 | F39: 0 | G39: =E39-D39 -> 4.5 | H39: STC
A40: OshKosh | B40: blue thick cardigan | C40: 4 | D40: 2.5 | E40: 15 | F40: 0 | G40: =E40-F40-D40 -> 12.5
A41: PACT | B41: stripe colorful sweater | C41: S | D41: 1.5 | E41: 20 | F41: 4.55 | G41: =E41-F41-D41 -> 13.95
A42: petit bateau | B42: 2 onesies | C42: 1mo | D42: 0 | E42: 5 | F42: 0.4 | G42: =E42-F42-D42 -> 4.6
A43: sergent major | B43: floral dress | C43: 1 | D43: 0 | E43: 10 | F43: 0.4 | G43: =E43-F43-D43 -> 9.6
A44: sezanne | B44: tan turtleneck | C44: XS | D44: 4 | E44: 10.5 | F44: 0 | G44: =E44-F44-D44 -> 6.5 | H44: STC
A45: stokke | B45: kids chair cushion | D45: 5.5 | E45: 25 | F45: 0 | G45: =E45-F45-D45 -> 19.5
A46: unknown | B46: mexican dress | C46: 10 | D46: 0 | E46: 10.5 | F46: 0 | G46: =E46-F46-D46 -> 10.5 | H46: STC | I46: 46116
A47: Tea collection | B47: pink floral skirt | C47: 5 | D47: 2 | E47: 4.5 | F47: 0 | G47: =E47-F47-D47 -> 2.5 | H47: STC
A48: The Kooples | B48: red sweater | C48: S | D48: 8.1 | E48: 15 | F48: 0 | G48: =E48-F48-D48 -> 6.9 | H48: STC
A49: Veja | B49: snickers | C49: 4 | D49: 0 | E49: 30 | F49: 0 | G49: =E49-F49-D49 -> 30
A50: Vertbaudet | B50: pink peacoat | C50: 12 | D50: 0 | E50: 13.5 | F50: 0 | G50: =E50-D50 -> 13.5 | H50: STC
A51: Vertbaudet | B51: pink sweater dress | C51: 4 | D51: 0 | E51: 10.5 | F51: 0 | G51: =E51-D51 -> 10.5 | H51: STC
A52: Wondernation | B52: blue/white stripes dress | C52: 8 | D52: 3 | E52: 4.5 | F52: 0 | G52: =E52-D52 -> 1.5 | H52: STC | I52: 46128
A53: Wondernation | B53: denim skirt | C53: 8 | D53: 0 | E53: 4.5 | F53: 0 | G53: =E53-D53 -> 4.5 | H53: STC | I53: 46123
A54: Wondernation | B54: grey cardigan | C54: 2 | D54: 3 | E54: 10 | F54: 0 | G54: =E54-F54-D54 -> 7
A55: Zara | B55: green tunique with birds | C55: 10 | D55: 2 | E55: 5 | F55: 0.4 | G55: =E55-F55-D55 -> 2.6

Sheet Home goods
A1: Brand | B1: what? | C1: size | D1: cost | E1: Sold | F1: Shipping | G1: Benefice net | H1: Market price | I1: Link
D2: =SUM(D4:D376) -> 803.11
A3: Aladdin | B3: Minuet bowl | D3: 5
A4: anri | B4: music box | D4: 2
A5: avon | B5: milk glass creamer | D5: 3
A6: aynsley | B6: wild tudor trinket | D6: 2
A7: baker and cold | B7: Old english handpainted / 1930 | C7: 7" plate | D7: 1.5 | H7: 20 | I7: https://www.ebay.com/itm/285534465724
A8: baker and cold | B8: Old english handpainted / 1930 / 2 bowls | D8: 3 | H8: 20
A9: baum bros | B9: small cream bowl | D9: 6
A10: Beatrix Potter | B10: peter rabbit mug | D10: 1.5
A11: Beatrix Potter | B11: peter rabbit mug | D11: 1.5
A12: Boleslawiec | B12: gravy sauce pan | D12: 15
A13: Boleslawiec | B13: lidded handled bowl | D13: 25
A14: Boop | B14: floral plate | D14: 3
A15: Boston | B15: handmade pot | D15: 1
A16: Castleton China | B16: gloria plate | D16: 1.5
A17: CBB | B17: handmade bowl | D17: 3.5
A18: Ceramiche Tadinate | B18: old italian dish | D18: 3.5 | H18: 30 | J18: https://www.ceramichetadinate.it/
A19: Churchill england | B19: 3 bowls, Fresco collection | C19: 8" | D19: 4.5 | I19: https://www.replacements.com/china-churchill-fresco-blue-coupe-soup-bowl/p/59337491
A20: CLG CO | B20: milk glass vase | D20: 3
A21: Colonial Candle | B21: vintage japanese candle holder | D21: 7
A22: Corelle by Corning | B22: 7 cups / Butterfly gold collection | C22: 3.5" | D22: 10.5 | H22: 10 | I22: https://www.replacements.com/china-corning-butterfly-gold-corelle/c/16777
A23: Corelle by Corning | B23: 8 saucers / butterfly gold collection | C23: 6" | D23: 5.6 | H23: 10 | I23: https://www.replacements.com/china-corning-butterfly-gold-corelle/c/16777
A24: corelle by Corning | B24: 2 saucers - blue pattern | D24: 1.4
A25: corning ware | B25: blue cornflower A1B | D25: 6.49
A26: corning ware | B26: blue cornflower P43B | D26: 5.98
A27: corning ware | B27: blue cornflower P4B | D27: 4.5
A28: corning ware | B28: Echalote P322 | D28: 7 | H28: keep | I28: https://www.ebay.com/itm/164033092126
A29: corning ware | B29: 3 qt casserole dish L'Echalote A3B | D29: 8 | H29: keep | J29: https://www.replacements.com/china-corning-spice-of-life-centura-3-quart-square-casserole-no-lid/p/20528411
A30: corning ware | B30: Echalote - A1B, 1 quart dish | D30: 4.7 | H30: keep
A31: corning ware | B31: 1.5qt casserole dish | D31: 4.5 | H31: keep | J31: https://www.replacements.com/china-corning-spice-of-life-centura-1-5-quart-square-casserole-no-lid/p/60528431
A32: corning ware | B32: Echalote P43B dish | D32: 3 | H32: keep
A33: corning ware | B33: wildflower dish A2B | D33: 8 | H33: 25 | I33: https://www.replacements.com/china-corning-wildflower-corelle-2-quart-square-casserole-no-lid/p/22831971
A34: corning ware | B34: F5B round dish with lid | D34: 6.5 | I34: https://www.replacements.com/china-corning-french-white-1-5-qt-round-covered-casserole/p/33858561
A35: corning ware | B35: round pie dish french white - F3B | D35: 4.5
A36: Country Harvest | B36: Apple pie dish | D36: 6
A37: Crate and Barrel | B37: golden candle holder, short | D37: 2
A38: Crate and Barrel | B38: tokyo small tray | D38: 1
A39: Crate and Barrel | B39: 4 green bowls | D39: 4
A40: Crate and Barrel | B40: 4 Winter Gems Appetizer plates | D40: 5
A41: Crate and Barrel | B41: white/green deep dish / salad bowl | D41: 9.5
A42: Crate and Barrel | B42: 2 coffee cups with red car | D42: 3
A43: Crate and Barrel | B43: clover dish | D43: 3.5 | H43: 15
A44: Crate and Barrel | B44: apero dish | D44: 2.5 | H44: 15
A45: Crate and Barrel | B45: blue tablecloth | D45: 6.5
A46: crown classics | B46: salt and pepper shakers | D46: 4
A47: crystal | B47: bohemian czeh crystal and frosted vase | D47: 5.5 | H47: 30 | I47: https://www.etsy.com/listing/1633681372/heavy-bohemian-czech-crystal-and-frosted?gpla=1&gao=1&
A48: Cristal France | B48: snowflake half globe | D48: 3
A49: daniel echter | B49: sucrier | D49: 3
A50: Dinny Myerson | B50: blue pitcher | D50: 6.6 | H50: keep
A51: Eisenberg Lozano | B51: silver wire basket MCM | D51: 3.5 | I51: https://www.etsy.com/listing/1633108520/vintage-italian-silver-wine-caddy
A52: Franciscan | B52: cream oval platter | D52: 4
A53: Gien | B53: white artichoke plate | D53: 4.5 | H53: keep
A54: Gien | B54: Filet bleu coffee pot | D54: 9.5 | H54: keep
A55: gourmet basics | B55: 4 cobalt mugs | D55: 4
A56: Guo Pei | B56: Legion of honor mug | D56: 3 | I56: https://www.ebay.com/itm/167620832815
A57: jars | B57: 5 blue plates | D57: 7
A58: Jeannette | B58: 2 Chantilly pink glasses | D58: 5.8 | H58: keep
A59: Johnson Bros England | B59: 5 cups and plates sets | D59: 11.5 | I59: https://www.replacements.com/china-johnson-brothers-willow-blue-black-and-blue-backstamps-older/c/140474
A60: Johnson Bros England | B60: 4 salad plates | D60: 8.9
A61: Johnson Bros England | B61: 6 small plates | D61: 8.9
A62: Karen Donleavy | B62: black dog mug | D62: 3
A63: le gourmet chef | B63: small blue dish | D63: 2.5 | H63: 5
A64: lenox chinastone | B64: Harvest small bowl | D64: 1
A65: lenox chinastone | B65: 4 blue pinstripe bowls | D65: 7
A66: lenox chinastone | B66: white bowl with gold | D66: 2
A67: Limoges | B67: square bowl | D67: 12.49
A68: lord nelson potter | B68: zebra plate | D68: 2.5 | J68: https://craftshero.com/lord-nelson-pottery/
A69: mat Ceramica | B69: blue bowl | D69: 1.5
A70: Mc Cluskey Pottery | B70: small beige vase with navy neck | D70: 2.5
A71: mikasa | B71: Terra stone Reims 7115 | D71: 2
A72: mushie | B72: 4 plates | D72: 5 | J72: https://mushie.com/products/square-dinnerware-plates-set-of-2?_pos=5&_fid=81f3369bf&_ss=c
A73: mushie | B73: 4 bowls | D73: 4.5 | J73: https://mushie.com/products/square-dinnerware-bowl-set-of-2?_pos=6&_fid=74887450e&_ss=c
A74: Noritake | B74: 4 bowls hello Spring | D74: 4
A75: Noritake | B75: Large dish Hello Spring | D75: 7
A76: Noritake | B76: Viceroy - Vegetable serving bowl | C76: 10" | D76: 3.5 | H76: 30 | I76: https://www.replacements.com/china-noritake-viceroy/c/69655?srsltid=AfmBOorAfvgPI4rhjCG5Sb_k6k7B9WqI5OHtS_5d4Tx4jtC0ksxef44F | J76: Made in Japan, 1975 - 1986, Ivory, Thin Gold Ring, Wide Gold Trim
A77: Noritake | B77: Viceroy - oval serving platter | C77: 13" | D77: 5.5 | H77: 40 | I77: https://www.replacements.com/china-noritake-viceroy/c/69655?srsltid=AfmBOorAfvgPI4rhjCG5Sb_k6k7B9WqI5OHtS_5d4Tx4jtC0ksxef44F | J77: Made in Japan, 1975 - 1986, Ivory, Thin Gold Ring, Wide Gold Trim
A78: Noritake | B78: Viceroy - 3 cups | D78: 4.5 | H78: 20 | I78: https://www.replacements.com/china-noritake-viceroy/c/69655?srsltid=AfmBOorAfvgPI4rhjCG5Sb_k6k7B9WqI5OHtS_5d4Tx4jtC0ksxef44F | J78: Made in Japan, 1975 - 1986, Ivory, Thin Gold Ring, Wide Gold Trim
A79: Norleans Japan | B79: vintage small vase | D79: 1
A80: Nymolle Denmark | B80: Set of 12 decorations | D80: 7 | H80: keep
A81: OMC Japan | B81: 3 small round trinkets | D81: 3
A82: Pam Edmondson | B82: red handmade tray | D82: 4
A83: Paul Mantonnet | B83: brown pottery | D83: 4
A84: Petit collage | B84: kids wood wall art | D84: 2.5
A85: Pfaltzgraff | B85: Yorktowne blue - Small dish | D85: 3.5
A86: Pfaltzgraff | B86: Yorktowne blue - Gravy boat | D86: 3.5
A87: Pfaltzgraff | B87: Yorktowne blue - Sugar bowl | D87: 2.5
A88: Pfaltzgraff | B88: Yorktowne blue - Creamer | D88: 2.5
A89: Pillivuyt | B89: white baking dish | D89: 3.5
A90: pyrex | B90: vintage deep dish pie plate | D90: 7 | H90: 20 | I90: https://www.replacements.com/china-pyrex-originals-clear-10-pie-baking-plate/p/118343191?utm_source=google_shopping&utm_medium=organic&utm_campaign=shopping_feed&gad_source=1&gclid=CjwKCAiAnKi8BhB0EiwA58DA4YhkmkEmmzxt2oVn3WVIrusShy_BJR8RrhneGkcgZKn1auoUoHQcPxoCMSkQAvD_BwE
A91: Rachel zoe | B91: 6 pumpkin napkins | D91: 4
A92: reed & barton | B92: shannon silverplate tray 1022 | D92: 5.5
A93: reed & barton | B93: 3800 sugar with lid - plated silver | D93: 6.5
A94: reed & barton | B94: 3800 sugar pot no lid - plated silver | D94: 4.5
A95: Royal copenhagen | B95: small white oval dish | D95: 1.25
A96: Royal Crownford | B96: 1979 Christmas plate | D96: 2.5 | H96: 15 | I96: https://www.etsy.com/listing/1805907561/royal-crownford-a-happy-holiday-to-you
A97: royal doulton | B97: 2 blue plates, the kirkwood, 8.5", stamped, no chip, no crack | D97: 5 | H97: 20 | I97: https://www.ebay.com/itm/334574052909 | J97: Made in england, 1950/1963, pattern D6314, Lambethware collection, beautiful blue bone china material with a printed backstamp. Add a touch of Victorian elegance to your table setting with this stunning set by Royal Doulton. Featuring a beautiful blue and white floral pattern. Hand wash only to keep their glossy finish looking beautiful. Each plate in this limited edition set is an original production of Blue and White Pottery from the United Kingdom. The backstamp is printed with the product line name "Kirkwood" and the brand "Royal Doulton." Ideal for collectors and dinner hosts | K97: History of Royal Doulton https://www.daltondatabank.org/Chronicles/Royal_Doulton.htm#:~:text=On%20September%2030%2C%202005%2C%20Doulton's,countryside%20south%20of%20the%20Potteries.
A98: royal M Japan | B98: 2 small round dishes | D98: 3
A99: Scentsational | B99: sage/magnolia candle | D99: 2.5
A100: Schmid | B100: small souffle dish | D100: 2
...

Sheet Home goods - Sold
A1: Brand | B1: what? | C1: size | D1: cost | E1: Sold | F1: Shipping | G1: Benefice net | H1: Market price | I1: Link
D2: =SUM(D3:D477) -> 678.3 | E2: =SUM(E3:E477) -> 2579.45 | F2: =SUM(F3:F477) -> 26.44
A3: Andrea by Sadek | B3: 2 saucers with flowers | D3: 3.5 | H3: 45767
A4: Anthropologie | B4: set of 4 green coasters | D4: 6 | E4: 15 | F4: 0 | G4: =E4-F4-D4 -> 9 | H4: 46131
A5: Anthropologie | B5: lion mug | D5: 1 | E5: 10 | F5: 0 | G5: =E5-F5-D5 -> 9 | H5: picnic
A6: Anthropologie | B6: ceramic french press | D6: 4.5 | E6: 50 | F6: 0 | G6: =E6-F6-D6 -> 45.5
A7: Anthropologie | B7: 4 plates | D7: 5 | E7: 15 | F7: 0 | G7: =E7-F7-D7 -> 10
A8: Anthropologie | B8: cat mug | D8: 1 | E8: 10 | F8: 0 | G8: =E8-F8-D8 -> 9
A9: At Home | B9: pink/yellow mug | D9: 1.5 | E9: 5 | F9: 0 | G9: =E9-F9-D9 -> 3.5
A10: Aza selection | B10: brown soliflore | E10: 10 | F10: 0 | G10: =E10-F10-D10 -> 10
A11: Beatrix Potter | B11: piggybank | D11: 3.5 | H11: 45893
A12: Beatrix Potter | B12: Benjamin bunny mug | D12: 1.5 | E12: 10 | F12: 0 | G12: =E12-F12-D12 -> 8.5 | H12: 46131
A13: Beatrix Potter | B13: Benjamin bunny mug | D13: 1.5 | E13: 10 | F13: 0 | G13: =E13-F13-D13 -> 8.5 | H13: 46131
A14: Beatrix Potter | B14: Small peter rabbit cup | D14: 1.5 | E14: 10 | F14: 0 | G14: =E14-F14-D14 -> 8.5 | H14: 46131
A15: Beatrix Potter | B15: Small peter rabbit cup | D15: 1.5 | E15: 10 | F15: 0 | G15: =E15-F15-D15 -> 8.5 | H15: 46131
A16: better homes & gardens | B16: Jute tablerunner | D16: 3 | E16: 20 | F16: 0 | G16: =E16-F16-D16 -> 17 | H16: 46131
A17: Bia cordon bleu | B17: 4 large cheese plates | D17: 9.5 | H17: 45696 | I17: sold 25 | J17: https://www.etsy.com/listing/1484516007/camembert-depot-paris-four-plate-serving?ga_order=most_relevant&ga_search_type=all&ga_view_type=gallery&ga_search_query=bia+cordon+bleu+camembert&ref=sr_gallery-1-13&content_source=4caf86f05116436909f51f2249291922ec7bc4bb%253A1484516007&search_preloaded_img=1&organic_search_click=1
A18: Bia cordon bleu | B18: 4 small cheese plates | D18: 7.5 | H18: Solano stroll
A19: Biltons | B19: cat mug, made in England | D19: 2.5 | H19: Solano stroll
A20: Bluelounge | B20: desk | D20: 0 | E20: 220 | F20: 0 | G20: =E20-F20-D20 -> 220
A21: Bodum | B21: columbia french press | D21: 5.8 | E21: 40 | F21: 0 | G21: =E21-F21-D21 -> 34.2
A22: bodum | B22: columbia coffee maker | D22: 3.5 | E22: 30 | F22: 0 | G22: =E22-F22-D22 -> 26.5 | H22: 30 | I22: https://www.bodum.com/us/en/1308-16-bodum-columbia
A23: Booths China | B23: 1 round plate | D23: 4 | E23: 12 | F23: 0 | G23: =E23-D23 -> 8 | H23: 46131
A24: Booths China | B24: 1 oval dish | D24: 4 | E24: 15 | F24: 0 | G24: =E24-D24 -> 11 | H24: 46131
A25: Castleton China | B25: gloria small bowl | D25: 1.5 | E25: 5 | F25: 0 | G25: =E25-F25-D25 -> 3.5 | H25: picnic
A26: cb2 | B26: pillowcase | D26: 0 | E26: 10 | F26: 0 | G26: =E26-F26-D26 -> 10
A27: Christophe Pichon | B27: brown salad bowl | D27: 4.5 | E27: 15 | F27: 0 | G27: =E27-F27-D27 -> 10.5 | H27: picnic
A28: colorstax | B28: blue gratin dish | D28: 3.5 | H28: Solano stroll
A29: corelle by Corning | B29: 4 cups / Butterfly gold collection | D29: 8.8 | E29: 25 | F29: 0 | G29: =E29-F29-D29 -> 16.2 | H29: picnic
A30: corning ware | B30: french white cocotte 4L F14B | D30: 12.8 | E30: 35 | F30: 0 | G30: =E30-D30 -> 22.2 | I30: https://www.etsy.com/listing/1182568373/corning-ware-french-white-f-14-b-4-liter?show_sold_out_detail=1&ref=nla_listing_details
A31: corning ware | B31: buffet server B4B, 4qt | D31: 17.2 | E31: 50 | F31: 0 | G31: =E31-F31-D31 -> 32.8 | I31: https://www.moose-r-us.com/shop/vintage-corning-ware-buffet-server-4-quart-white-casserole-stew-usa-cooking-pot/
A32: Crate and Barrel | B32: blue/green speckled ombre barrel vase | C32: 6.25”x 7” | D32: 4.5 | H32: 45935 | I32: https://www.ebay.com/itm/386942557783 | J32: made in Portugal, stamped, The blue color has an eggshell finish and the green is glossy.
A33: Crate and Barrel | B33: set of 4 east coast trays | D33: 5 | H33: 45893
A34: Crate and Barrel | B34: set of 4 mugs | D34: 6 | E34: 20 | F34: 0 | G34: =E34-F34-D34 -> 14
A35: Crate and Barrel | B35: white chip & dip | D35: 4 | E35: 5 | F35: 0 | G35: =E35-D35 -> 1 | H35: 15 | I35: https://www.ebay.com/itm/313911293815
A36: Crate and Barrel | B36: 2 martini glasses, crafted in mexico, Granada collection | C36: 5.5 x 6.5 | D36: 3 | E36: 20 | F36: 0 | G36: =E36-F36-D36 -> 17 | H36: picnic | I36: https://www.ebay.com/itm/195760494918 | J36: hand blown in Mexico, color swirl, no chips or cracks
A37: Crate and Barrel | B37: golden candle holder | D37: 3 | E37: 20 | F37: 0 | G37: =E37-F37-D37 -> 17 | H37: picnic
A38: Crate and Barrel | B38: ceramic sake bottle | C38: 6" tall | D38: 2.5 | H38: 45767 | I38: https://poshmark.com/listing/Crate-and-Barrel-silver-white-ceramic-sake-bottle-vase-677e7e0f64f5a286526f0d21
A39: cristal d'arques | B39: alexandrite neodymium crystal vase | D39: 3.5 | H39: 45767 | I39: https://www.etsy.com/listing/1689223138/vase-vintage-en-cystal-pae-crystal
A40: Crystal clear | B40: 2 candle holders made in Romania | D40: 10 | E40: 45 | F40: 0 | G40: =E40-F40-D40 -> 35 | H40: 40 | I40: https://www.etsy.com/listing/1520019982/crystal-clear-hand-crafted-crystal?ref=share_v4_lx
A41: Darzzi | B41: grey/white cotton throw | H41: 45893
A42: Emile Henry | B42: Green Pie dish | D42: 4.5 | H42: 45893
A43: FAB | B43: star wars piggy bank | D43: 4.5 | E43: 20 | F43: 0 | G43: =E43-F43-D43 -> 15.5
A44: Fitz and floyd | B44: 1978 owl tea pot + 2 cups | D44: 11 | E44: 50 | F44: 0 | G44: =E44-F44-D44 -> 39 | H44: 50
A45: gail pittman | B45: cream pie dish, hospitality collection | D45: 5.5 | H45: 45767
A46: George Jones and Sons | B46: Crescent Ivory tea pot | D46: 5 | E46: 25 | F46: 0 | G46: =E46-F46-D46 -> 20
A47: Goel brass | B47: small round box | D47: 2.5 | E47: 20 | F47: 0 | G47: =E47-F47-D47 -> 17.5
A48: Habitat | B48: 3 candle holders | D48: 0 | E48: 40 | F48: 0 | G48: =E48-F48-D48 -> 40
A49: Halcyon | B49: london tea pot | D49: 5.5 | E49: 40 | F49: 0 | G49: =E49-F49-D49 -> 34.5 | H49: 40
A50: Haviland | B50: 4 Baltimore rose small dishes | D50: 5.5 | H50: 45767 | I50: https://www.replacements.com/china-haviland-schleiger-1151a/c/33129
A51: ikea | B51: beige/black tablerunner | D51: 3 | H51: 45893
A52: ikea | B52: set of 3 candlesticks | D52: 6 | H52: solano stroll
A53: ikea | B53: set of 3 candlesticks | D53: 6 | E53: 20 | F53: 0 | G53: =E53-F53-D53 -> 14
A54: ikea | B54: set of 3 candlesticks | D54: 6 | E54: 20 | F54: 0 | G54: =E54-F54-D54 -> 14
A55: Itsuko | B55: Itsuko Zenitani Studio bowl | D55: 3.5 | E55: 30 | F55: 0 | G55: =E55-F55-D55 -> 26.5 | H55: 30
A56: Jansport | B56: backpack | D56: 4.25 | E56: 20 | F56: 0 | G56: =E56-F56-D56 -> 15.75
A57: Karen Donleavy | B57: black cat mug | D57: 2 | E57: 10 | F57: 0 | G57: =E57-F57-D57 -> 8 | H57: 46131
A58: Kinbi | B58: navy floral fabric | D58: 1.5 | E58: 15 | F58: 0 | G58: =E58-D58 -> 13.5
A59: Kinbi | B59: rabbit navy fabric | D59: 1.5 | E59: 20 | F59: 0 | G59: =E59-D59 -> 18.5
A60: laura ashley | B60: 1976 salad bowl | D60: 5 | H60: 45696 | I60: sold 25
A61: le creuset | B61: large oval pan #36 | D61: 17.5 | E61: 40 | F61: 0 | G61: =E61-F61-D61 -> 22.5 | H61: picnic | J61: https://www.ebay.com/itm/126919777906
A62: Lego | B62: Dumbledore office | E62: 50 | F62: 0 | G62: =E62-F62-D62 -> 50
A63: Lego | B63: Chamber of Secrets + bus | E63: 100 | F63: 0 | G63: =E63-F63-D63 -> 100
A64: Lego | B64: chess set | E64: 50 | F64: 0 | G64: =E64-F64-D64 -> 50
A65: Limoges | B65: saucier | D65: 8.49 | H65: 45935
A66: Margaret Keane | B66: polar bear plate 1990 | D66: 2.5 | E66: 20 | F66: 0 | G66: =E66-F66-D66 -> 17.5 | H66: 20 | I66: https://www.etsy.com/listing/1746243140/vintage-1990-the-franklin-mint-gentle?ga_order=most_relevant&ga_search_type=all&ga_view_type=gallery&ga_search_query=margaret+keane+plate&ref=sr_gallery-1-9&pro=1&frs=1&content_source=95ddcdc73ecc39dc60533fe4412b375fdf7b5a8f%253A1746243140&organic_search_click=1
A67: metlox | B67: bandero 13" oval serving platter / poppytrail | D67: 2.5 | H67: 45893 | I67: https://www.etsy.com/nz/listing/1761699686/metlox-poppytrail-vernon-porcelain
A68: MH | B68: handmade MCM vase | D68: 3.25 | H68: 45935
A69: MH | B69: handmade MC pottery | D69: 2.25 | H69: solano stroll
A70: Mikasa | B70: 4 bowls, Blue Thunder collection | D70: =0.85*4 -> 3.4 | E70: 30 | F70: 0 | G70: =E70-F70-D70 -> 26.6 | H70: 40
A71: Mikasa | B71: stone manor milk pot | D71: 2.5 | H71: 45767
A72: MSI japan | B72: colonial stoneware / 5 cups | D72: 7.5 | H72: 45767 | I72: https://poshmark.com/listing/COLONIAL-Stoneware-CUP-and-SAUCER-Made-in-Japan-Colonial-Stoneware-64fdcbd88634cb7853aaae46?srsltid=AfmBOooefT7AvICZ7U741asjHjArYuzMUuKLRJAWel__2DkG0lgOfgnLDM4#utm_source=gdm_unpaid
A73: Ninja | B73: air fryer | D73: 17 | E73: 50 | F73: 0 | G73: =E73-F73-D73 -> 33
A74: Noritake | B74: 4 misty isle cereal bowls | D74: 8 | E74: 25 | F74: 0 | G74: =E74-F74-D74 -> 17 | H74: 40
A75: Noritake | B75: 4 tea cups | D75: 10 | E75: 20 | F75: 0 | G75: =E75-F75-D75 -> 10 | H75: 30
A76: Pfaltzgraff | B76: Yorktowne blue - utensils pot | D76: 4.5 | H76: 45935
A77: Pfaltzgraff | B77: Juniper Sugar bowl and lid | D77: 2.5 | H77: solano stroll | J77: Vintage, made in the 90'
A78: Pfaltzgraff | B78: Yorktowne blue - water pot | D78: 6.5 | E78: 20 | F78: 0 | G78: =E78-F78-D78 -> 13.5 | H78: picnic
A79: Pickard | B79: small bowl, Diplomat collection | C79: 5" | D79: 3.5 | H79: 45767 | I79: https://www.replacements.com/china-pickard-diplomat/c/75454?srsltid=AfmBOoozHiGz3Fphd7CwNGJcZh42MpYe7ye6iHwt7xXzJPM8iBAIISN_
A80: Pickenpaugh pottery | B80: blue/brown bowl, signed | D80: 1.8 | E80: 20 | F80: 0 | G80: =E80-F80-D80 -> 18.2 | H80: picnic
A81: porcelaine de paris | B81: floral dutch oven | D81: 6.5 | H81: 45935
A82: Portmeirion | B82: botanic garden dog rose tea pot 1972 | D82: 5.5 | E82: 40 | F82: 0 | G82: =E82-F82-D82 -> 34.5 | H82: 60 | I82: https://www.etsy.com/listing/1766421259/portmeirion-botanic-garden-dog-rose-1972?show_sold_out_detail=1&ref=nla_listing_details
A83: portmeirion | B83: peaches large dish | D83: 6 | E83: 10 | F83: 0 | G83: =E83-D83 -> 4
A84: Pottery Barn | B84: 6 Bongo mugs | D84: 15 | E84: 30 | F84: 0 | G84: =E84-F84-D84 -> 15
A85: Printemps | B85: large yellow platter | D85: 0 | H85: 45696 | I85: sold 20
A86: Queenwest | B86: blue cotton throw | D86: 8.5 | E86: 25 | F86: 0 | G86: =E86-F86-D86 -> 16.5 | H86: picnic
A87: Quicksilver | B87: blue tray | D87: 3 | E87: 20 | F87: 0 | G87: =E87-F87-D87 -> 17 | H87: picnic
A88: Rae Dunn | B88: best nana box | D88: 2.5 | E88: 10 | F88: 0 | G88: =E88-F88-D88 -> 7.5
A89: Restauration Hardware | B89: 2 silver platted candlesticks | D89: 7 | E89: 40 | F89: 0 | G89: =E89-F89-D89 -> 33 | H89: picnic
A90: Rosanna | B90: Travel tip France trincket | D90: 3.5 | E90: 10 | F90: 0 | G90: =E90-F90-D90 -> 6.5 | H90: picnic
A91: Rosanna | B91: patio party / bon voyage | D91: 2.5 | E91: 10 | F91: 0 | G91: =E91-F91-D91 -> 7.5
A92: Rosanna | B92: patio party / havana | D92: 2.5 | E92: 10 | F92: 0 | G92: =E92-F92-D92 -> 7.5
A93: Rosanna | B93: patio party / cote d'azur | D93: 4.5 | E93: 10 | F93: 0 | G93: =E93-F93-D93 -> 5.5
A94: Safi | B94: small spice pottery | D94: 1.5 | E94: 15 | F94: 0 | G94: =E94-F94-D94 -> 13.5 | H94: picnic
A95: simplystoneware | B95: garlic graterq | D95: 2.5 | E95: 15 | F95: 0 | G95: =E95-F95-D95 -> 12.5
A96: Slant collection | B96: hexagone flower tray | D96: 1.5 | H96: 45767
A97: soule studio | B97: large blue bowl | D97: 7.5 | H97: 45935
A98: soule studio | B98: large red bowl | D98: 7.5 | E98: 52 | F98: 11.74 | G98: =E98-D98-F98 -> 32.76
A99: starbucks | B99: 2001 talavera mug | D99: 1.5 | H99: 45696 | I99: sold 15
A100: Stoneware | B100: 4 pink bowls, made in Japan | D100: 4 | E100: 20 | F100: 0 | G100: =E100-F100-D100 -> 16
...
